fastapitemplatewizard/__init__.py
fastapitemplatewizard/constants.py
fastapitemplatewizard/main.py
fastapitemplatewizard/utils.py
FastAPI_TemplateWizard-0.1.5.dist-info/LICENSE
FastAPI_TemplateWizard-0.1.5.dist-info/METADATA
FastAPI_TemplateWizard-0.1.5.dist-info/WHEEL
FastAPI_TemplateWizard-0.1.5.dist-info/entry_points.txt
FastAPI_TemplateWizard-0.1.5.dist-info/top_level.txt
FastAPI_TemplateWizard-0.1.5.dist-info/RECORD
